extras/__init__.py
extras/divide.py
extras/multiply.py
extras/power.py
kul_module-0.0.0.dist-info/METADATA
kul_module-0.0.0.dist-info/WHEEL
kul_module-0.0.0.dist-info/top_level.txt
kul_module-0.0.0.dist-info/RECORD
